Metadata-Version: 2.1
Name: image_processing-class
Version: 0.0.1
Summary: Class - Image processing. The original project belongs to Karina Tiemi Kato.
Home-page: https://github.com/rdfalmeida/image-processing-package.git
Author: Rodolfo Almeida
Author-email: rdfalmeida@protonmail.com
Requires-Python: >=3.13
Requires-Dist: matplotlib
Requires-Dist: numpy
Requires-Dist: scikit-image >=0.16.1
